{
  "gate": 64,
  "gateName": "Before Completion",
  "mainQuestTheme": "Turning scattered mental pressure into usable clarity before acting too soon.",
  "mainQuestContent": [
    {
      "gate": 64,
      "line": 1,
      "gateLine": "64.1",
      "title": "Pressure at the Threshold",
      "hero": {
        "mainQuest": "Pattern Resolution",
        "sourceLine": "Purpose · Design Earth · I Ching 64.1",
        "questState": "Unsorted",
        "atmosphericSubtitle": "The pattern is not ready. The pressure still wants an answer."
      },
      "questBrief": {
        "collapsedPreview": "The pieces are present, but not placed.",
        "mission": "Hold the first layer of confusion without rushing it into certainty.",
        "fieldPrompt": "Look for the one piece that keeps demanding premature closure.",
        "livePrompt": "What are you trying to solve too early?"
      },
      "fieldBriefing": {
        "collapsedPreview": "Stay with the first incomplete signal.",
        "whatThisQuestIsAbout": "This quest begins before the pattern has enough structure to reveal itself. Information arrives in pieces, but the mind wants to seal it into an answer before the foundation is stable.",
        "whyThisMattersNow": "Early certainty creates a false base. The work is to hold the beginning without letting pressure choose the conclusion.",
        "primaryRecognitionTrigger": "You grab the first explanation because not knowing feels exposed.",
        "livePrompt": "Where are you treating one clue like the whole answer?"
      },
      "assetsAndFriction": {
        "collapsedPreview": "Foundation comes before interpretation.",
        "questTrap": "You mistake relief for clarity.",
        "questAssets": [
          "first-signal detection",
          "mental containment",
          "pattern patience"
        ],
        "frictionSignals": [
          "locking onto the first reason",
          "asking for certainty before enough is visible",
          "building a conclusion from one fragment"
        ],
        "livePrompt": "Watch where relief arrives faster than truth."
      },
      "groundingEffect": {
        "collapsedPreview": "Let the pressure drop lower.",
        "groundingProtocol": [
          "soften the forehead",
          "drop breath into belly",
          "release the grip in your hands"
        ],
        "somaticShift": "The body stops chasing the answer and settles under the question.",
        "bodyCheckPrompt": "Is your head reaching forward, or can your belly hold the unknown?"
      },
      "unlockCondition": {
        "collapsedPreview": "Do not crown the first answer.",
        "questKey": "Name the first fragment → refuse final meaning → wait for a second confirming signal",
        "embodiedSignal": "The body feels less urgent even though the question remains open.",
        "ritualPrompt": "Write the first clue down without deciding what it means yet.",
        "alignmentReminder": "A fragment is not a pattern.",
        "livePrompt": "Wait for one more piece before naming the truth."
      },
      "driftPattern": [
        "using one clue as proof",
        "ending inquiry before the pattern forms"
      ]
    },
    {
      "gate": 64,
      "line": 2,
      "gateLine": "64.2",
      "title": "Natural Pattern Recognition",
      "hero": {
        "mainQuest": "Pattern Resolution",
        "sourceLine": "Purpose · Design Earth · I Ching 64.2",
        "questState": "Glimmering",
        "atmosphericSubtitle": "The answer appears sideways before the mind can justify it."
      },
      "questBrief": {
        "collapsedPreview": "The pattern flashes before it explains itself.",
        "mission": "Trust the clean recognition without forcing it into a full argument.",
        "fieldPrompt": "Notice where the answer arrives as shape, not proof.",
        "livePrompt": "What do you recognize before you can explain?"
      },
      "fieldBriefing": {
        "collapsedPreview": "Let recognition arrive before reasoning.",
        "whatThisQuestIsAbout": "This line sees the pattern before the details have organized. The insight is real, but it is delicate; too much explanation too soon can distort the signal.",
        "whyThisMattersNow": "The gift is early recognition. The danger is trying to prove the recognition before it has matured.",
        "primaryRecognitionTrigger": "You know what it is, then ruin it trying to justify why.",
        "livePrompt": "Where does your knowing get weaker when you over-explain it?"
      },
      "assetsAndFriction": {
        "collapsedPreview": "Recognition is faster than proof.",
        "questTrap": "You explain the signal until it loses shape.",
        "questAssets": [
          "intuitive pattern sight",
          "early signal recognition",
          "quiet mental accuracy"
        ],
        "frictionSignals": [
          "over-explaining a clean read",
          "doubting the first true shape",
          "forcing proof before timing supports it"
        ],
        "livePrompt": "Watch where clarity turns into performance."
      },
      "groundingEffect": {
        "collapsedPreview": "Keep the knowing quiet in the body.",
        "groundingProtocol": [
          "relax the jaw",
          "let breath settle behind the ribs",
          "soften the eyes before speaking"
        ],
        "somaticShift": "The insight stays intact because the body does not rush to defend it.",
        "bodyCheckPrompt": "Does your throat tighten when you try to prove what you already see?"
      },
      "unlockCondition": {
        "collapsedPreview": "Recognize first, explain later.",
        "questKey": "Notice the pattern → hold it without defending → speak only the part that is clear",
        "embodiedSignal": "The body stays quiet even while the mind sees the shape.",
        "ritualPrompt": "Say only the cleanest sentence and leave the rest unfinished.",
        "alignmentReminder": "Over-proof can break an accurate read.",
        "livePrompt": "Speak the shape, not the whole theory."
      },
      "driftPattern": [
        "weakening recognition through explanation",
        "turning a clean insight into a case to defend"
      ]
    },
    {
      "gate": 64,
      "line": 3,
      "gateLine": "64.3",
      "title": "Confusion Through Collision",
      "hero": {
        "mainQuest": "Pattern Resolution",
        "sourceLine": "Purpose · Design Earth · I Ching 64.3",
        "questState": "Scrambling",
        "atmosphericSubtitle": "The pieces collide until the false order breaks."
      },
      "questBrief": {
        "collapsedPreview": "The wrong fit teaches the real pattern.",
        "mission": "Use the failed interpretation as feedback instead of proof that nothing makes sense.",
        "fieldPrompt": "Track which explanation collapses the moment it touches reality.",
        "livePrompt": "What keeps breaking when tested?"
      },
      "fieldBriefing": {
        "collapsedPreview": "The pattern forms through failed fits.",
        "whatThisQuestIsAbout": "This line learns by trying to connect pieces that do not always belong together. Confusion intensifies when the mind keeps forcing a fit instead of noticing what the failure reveals.",
        "whyThisMattersNow": "The breakdown is useful when it exposes the wrong structure. It becomes costly when the same false pattern is rebuilt again.",
        "primaryRecognitionTrigger": "You keep rearranging the same pieces and calling it progress.",
        "livePrompt": "Where is the same failed answer wearing a new shape?"
      },
      "assetsAndFriction": {
        "collapsedPreview": "Bad fits reveal the structure.",
        "questTrap": "You keep testing what already failed.",
        "questAssets": [
          "error detection",
          "adaptive sorting",
          "friction-based learning"
        ],
        "frictionSignals": [
          "forcing unrelated pieces together",
          "restarting the same interpretation",
          "ignoring what the failed fit exposed"
        ],
        "livePrompt": "Watch the part of the pattern that keeps rejecting your answer."
      },
      "groundingEffect": {
        "collapsedPreview": "Stop solving from the skull.",
        "groundingProtocol": [
          "lengthen the spine",
          "release tension behind the eyes",
          "exhale before choosing the next piece"
        ],
        "somaticShift": "The body stops bracing against confusion and begins sorting one contact point at a time.",
        "bodyCheckPrompt": "Are you tightening around the answer, or feeling where the fit fails?"
      },
      "unlockCondition": {
        "collapsedPreview": "Use the failure as data.",
        "questKey": "Test one connection → mark the failure honestly → change the next attempt",
        "embodiedSignal": "The body feels clearer after admitting what does not fit.",
        "ritualPrompt": "Remove one false link before adding another idea.",
        "alignmentReminder": "A failed fit is information, not defeat.",
        "livePrompt": "Let the broken connection teach the next move."
      },
      "driftPattern": [
        "rebuilding the same false explanation",
        "treating confusion as a reason to force harder"
      ]
    },
    {
      "gate": 64,
      "line": 4,
      "gateLine": "64.4",
      "title": "Shared Mental Framework",
      "hero": {
        "mainQuest": "Pattern Resolution",
        "sourceLine": "Purpose · Design Earth · I Ching 64.4",
        "questState": "Arranging",
        "atmosphericSubtitle": "The pattern sharpens when it is placed into a shared frame."
      },
      "questBrief": {
        "collapsedPreview": "Clarity improves when the frame is shared.",
        "mission": "Bring the scattered pieces into a structure others can respond to.",
        "fieldPrompt": "Find the frame that makes the confusion discussable.",
        "livePrompt": "Who needs the pattern made visible?"
      },
      "fieldBriefing": {
        "collapsedPreview": "Make the confusion shareable.",
        "whatThisQuestIsAbout": "This line organizes uncertainty through relationship, language, and shared framing. The pattern becomes clearer when it is placed where others can see, test, and respond to it.",
        "whyThisMattersNow": "Private confusion loops. Shared structure reveals gaps, support, and next steps.",
        "primaryRecognitionTrigger": "You keep it in your head so no one can challenge the frame.",
        "livePrompt": "Where would clarity improve if someone else could see the map?"
      },
      "assetsAndFriction": {
        "collapsedPreview": "The frame needs witnesses.",
        "questTrap": "You organize alone until the pattern goes stale.",
        "questAssets": [
          "shared framing",
          "collaborative sorting",
          "communicable structure"
        ],
        "frictionSignals": [
          "withholding the unfinished map",
          "asking for input too late",
          "protecting a private interpretation"
        ],
        "livePrompt": "Watch where secrecy keeps the confusion intact."
      },
      "groundingEffect": {
        "collapsedPreview": "Open the chest before explaining.",
        "groundingProtocol": [
          "expand breath across chest",
          "relax the tongue",
          "plant both feet before presenting"
        ],
        "somaticShift": "The body becomes available for response instead of defending the private map.",
        "bodyCheckPrompt": "Can your chest stay open while someone tests your frame?"
      },
      "unlockCondition": {
        "collapsedPreview": "Expose the frame before it hardens.",
        "questKey": "Draft the pattern → share the unfinished frame → revise from real response",
        "embodiedSignal": "The body stays steady while the structure is questioned.",
        "ritualPrompt": "Show the current map before polishing it.",
        "alignmentReminder": "A shared frame can reveal what private certainty hides.",
        "livePrompt": "Let one trusted person test the pattern."
      },
      "driftPattern": [
        "protecting unfinished thoughts from feedback",
        "staying private until the structure becomes rigid"
      ]
    },
    {
      "gate": 64,
      "line": 5,
      "gateLine": "64.5",
      "title": "Projected Resolution",
      "hero": {
        "mainQuest": "Pattern Resolution",
        "sourceLine": "Purpose · Design Earth · I Ching 64.5",
        "questState": "Pressurized",
        "atmosphericSubtitle": "People expect the answer before the pattern is complete."
      },
      "questBrief": {
        "collapsedPreview": "Others look to you for closure.",
        "mission": "Hold projected certainty without pretending the answer is finished.",
        "fieldPrompt": "Separate the pressure to resolve from the pattern actually resolving.",
        "livePrompt": "Who is asking you to know before you know?"
      },
      "fieldBriefing": {
        "collapsedPreview": "Pressure is not proof.",
        "whatThisQuestIsAbout": "This line attracts expectation. Others may treat your partial clarity as final truth, and the mind feels pulled to deliver resolution before the pattern has fully arrived.",
        "whyThisMattersNow": "False certainty spreads quickly here. The real power is naming what is clear without pretending the rest is complete.",
        "primaryRecognitionTrigger": "You sound certain because they need you to be.",
        "livePrompt": "Where are you performing closure for someone else's anxiety?"
      },
      "assetsAndFriction": {
        "collapsedPreview": "Influence requires honest limits.",
        "questTrap": "You become the answer before the answer exists.",
        "questAssets": [
          "public synthesis",
          "pressure steadiness",
          "responsible clarification"
        ],
        "frictionSignals": [
          "speaking past the evidence",
          "absorbing others' urgency",
          "turning partial insight into a final call"
        ],
        "livePrompt": "Watch where being trusted becomes pressure to overstate."
      },
      "groundingEffect": {
        "collapsedPreview": "Hold your center under expectation.",
        "groundingProtocol": [
          "anchor breath in belly",
          "relax the sternum",
          "slow the first sentence"
        ],
        "somaticShift": "The body stops rising into performance and returns to measured truth.",
        "bodyCheckPrompt": "Are you speaking from clarity, or from the pressure to relieve the room?"
      },
      "unlockCondition": {
        "collapsedPreview": "Separate clarity from performance.",
        "questKey": "Name what is clear → mark what is unfinished → refuse finality under pressure",
        "embodiedSignal": "The body stays grounded even when others want certainty.",
        "ritualPrompt": "Say the boundary of the answer before giving the answer.",
        "alignmentReminder": "Authority collapses when certainty is borrowed.",
        "livePrompt": "Tell the truth without completing the pattern for them."
      },
      "driftPattern": [
        "performing certainty for others",
        "overstating clarity to reduce pressure"
      ]
    },
    {
      "gate": 64,
      "line": 6,
      "gateLine": "64.6",
      "title": "Completion Without Closure",
      "hero": {
        "mainQuest": "Pattern Resolution",
        "sourceLine": "Purpose · Design Earth · I Ching 64.6",
        "questState": "Suspended",
        "atmosphericSubtitle": "The pattern is visible, but the final move has not arrived."
      },
      "questBrief": {
        "collapsedPreview": "Completion waits past the answer.",
        "mission": "Let the pattern remain unfinished until timing, evidence, and readiness align.",
        "fieldPrompt": "Notice where almost-complete still wants one more condition.",
        "livePrompt": "What is clear, but not ready?"
      },
      "fieldBriefing": {
        "collapsedPreview": "Do not force the final seal.",
        "whatThisQuestIsAbout": "This line stands near completion but cannot force the last piece into place. The pattern may be mostly visible, yet the final movement depends on timing rather than mental pressure.",
        "whyThisMattersNow": "Premature closure reduces the intelligence of the whole process. Waiting becomes active when it protects the final form.",
        "primaryRecognitionTrigger": "You call it done because waiting one more step feels unbearable.",
        "livePrompt": "Where is the almost-finished thing asking not to be sealed yet?"
      },
      "assetsAndFriction": {
        "collapsedPreview": "The last piece has timing.",
        "questTrap": "You finish the pattern to escape the pressure.",
        "questAssets": [
          "completion discernment",
          "timing awareness",
          "final-stage restraint"
        ],
        "frictionSignals": [
          "sealing the answer too soon",
          "mistaking exhaustion for completion",
          "forcing closure because the pattern is almost clear"
        ],
        "livePrompt": "Watch where impatience disguises itself as readiness."
      },
      "groundingEffect": {
        "collapsedPreview": "Let the spine hold the pause.",
        "groundingProtocol": [
          "lengthen the back of the neck",
          "settle breath down the spine",
          "release the chest from urgency"
        ],
        "somaticShift": "The body can hold almost-complete without collapsing into a final move.",
        "bodyCheckPrompt": "Can your spine stay steady while the answer remains unfinished?"
      },
      "unlockCondition": {
        "collapsedPreview": "Wait until completion is real.",
        "questKey": "See the near-complete pattern → pause before closure → act only when the last condition arrives",
        "embodiedSignal": "The body feels steady enough to leave the ending open.",
        "ritualPrompt": "Name the missing condition before calling it complete.",
        "alignmentReminder": "Almost finished is not finished.",
        "livePrompt": "Protect the final step from premature closure."
      },
      "driftPattern": [
        "forcing closure at the edge of completion",
        "mistaking relief for readiness"
      ]
    }
  ],
  "perkTrees": [
    {
      "id": "perk-tree-64-1-v2",
      "mainQuestId": "purpose-64-1",
      "mainQuestName": "Pattern Resolution",
      "sourceLine": "Purpose · Design Earth · I Ching 64.1",
      "questState": "Unsorted",
      "subtitle": "Develop the capacities behind Pressure at the Threshold.",
      "nodes": [
        {
          "branch": "Root",
          "name": "Pattern Resolution",
          "state": "Core",
          "description": "This path develops the ability to turn incomplete mental pressure into usable clarity through pressure at the threshold.",
          "effect": "Confusion becomes workable when the pattern is not forced into false certainty.",
          "developmentCue": "Notice the difference between pressure and real pattern.",
          "masteryMarker": "Unfinished information can be held without rushing into closure."
        },
        {
          "branch": "Awareness",
          "name": "Seeing the First Fragment",
          "state": "Emerging",
          "description": "You learn to notice which part of the pattern is actually visible.",
          "effect": "Fragments stop pretending to be the whole picture.",
          "developmentCue": "Identify the clearest piece without enlarging it.",
          "masteryMarker": "You can separate a real signal from a completed story."
        },
        {
          "branch": "Embodiment",
          "name": "Holding Initial Uncertainty",
          "state": "Emerging",
          "description": "The body learns to stay steady while the mind has not finished sorting.",
          "effect": "Action slows enough for real structure to appear.",
          "developmentCue": "Let the body settle before naming the answer.",
          "masteryMarker": "You remain physically steady without needing instant resolution."
        },
        {
          "branch": "Field",
          "name": "Foundational Sorting",
          "state": "Emerging",
          "description": "The surrounding field becomes easier to read when the pattern is not forced.",
          "effect": "Confusion becomes organized through timing, response, and visible feedback.",
          "developmentCue": "Let the field show which pieces belong together.",
          "masteryMarker": "The pattern can clarify without being mentally cornered."
        },
        {
          "branch": "Mastery",
          "name": "Waiting for the Pattern to Form",
          "state": "Mastery",
          "description": "The full path matures into clean resolution without premature closure.",
          "effect": "Clarity arrives with enough structure to support action.",
          "developmentCue": "Wait until the pattern can carry the next move.",
          "masteryMarker": "You complete the thought only when the form is ready."
        }
      ]
    },
    {
      "id": "perk-tree-64-2-v2",
      "mainQuestId": "purpose-64-2",
      "mainQuestName": "Pattern Resolution",
      "sourceLine": "Purpose · Design Earth · I Ching 64.2",
      "questState": "Glimmering",
      "subtitle": "Develop the capacities behind Natural Pattern Recognition.",
      "nodes": [
        {
          "branch": "Root",
          "name": "Pattern Resolution",
          "state": "Core",
          "description": "This path develops the ability to turn incomplete mental pressure into usable clarity through natural pattern recognition.",
          "effect": "Confusion becomes workable when the pattern is not forced into false certainty.",
          "developmentCue": "Notice the difference between pressure and real pattern.",
          "masteryMarker": "Unfinished information can be held without rushing into closure."
        },
        {
          "branch": "Awareness",
          "name": "Early Pattern Recognition",
          "state": "Emerging",
          "description": "You learn to notice which part of the pattern is actually visible.",
          "effect": "Fragments stop pretending to be the whole picture.",
          "developmentCue": "Identify the clearest piece without enlarging it.",
          "masteryMarker": "You can separate a real signal from a completed story."
        },
        {
          "branch": "Embodiment",
          "name": "Quiet Knowing",
          "state": "Emerging",
          "description": "The body learns to stay steady while the mind has not finished sorting.",
          "effect": "Action slows enough for real structure to appear.",
          "developmentCue": "Let the body settle before naming the answer.",
          "masteryMarker": "You remain physically steady without needing instant resolution."
        },
        {
          "branch": "Field",
          "name": "Signal Preservation",
          "state": "Emerging",
          "description": "The surrounding field becomes easier to read when the pattern is not forced.",
          "effect": "Confusion becomes organized through timing, response, and visible feedback.",
          "developmentCue": "Let the field show which pieces belong together.",
          "masteryMarker": "The pattern can clarify without being mentally cornered."
        },
        {
          "branch": "Mastery",
          "name": "Recognizing Without Over-Proving",
          "state": "Mastery",
          "description": "The full path matures into clean resolution without premature closure.",
          "effect": "Clarity arrives with enough structure to support action.",
          "developmentCue": "Wait until the pattern can carry the next move.",
          "masteryMarker": "You complete the thought only when the form is ready."
        }
      ]
    },
    {
      "id": "perk-tree-64-3-v2",
      "mainQuestId": "purpose-64-3",
      "mainQuestName": "Pattern Resolution",
      "sourceLine": "Purpose · Design Earth · I Ching 64.3",
      "questState": "Scrambling",
      "subtitle": "Develop the capacities behind Confusion Through Collision.",
      "nodes": [
        {
          "branch": "Root",
          "name": "Pattern Resolution",
          "state": "Core",
          "description": "This path develops the ability to turn incomplete mental pressure into usable clarity through confusion through collision.",
          "effect": "Confusion becomes workable when the pattern is not forced into false certainty.",
          "developmentCue": "Notice the difference between pressure and real pattern.",
          "masteryMarker": "Unfinished information can be held without rushing into closure."
        },
        {
          "branch": "Awareness",
          "name": "Failure-Based Sorting",
          "state": "Emerging",
          "description": "You learn to notice which part of the pattern is actually visible.",
          "effect": "Fragments stop pretending to be the whole picture.",
          "developmentCue": "Identify the clearest piece without enlarging it.",
          "masteryMarker": "You can separate a real signal from a completed story."
        },
        {
          "branch": "Embodiment",
          "name": "Adaptive Reassembly",
          "state": "Emerging",
          "description": "The body learns to stay steady while the mind has not finished sorting.",
          "effect": "Action slows enough for real structure to appear.",
          "developmentCue": "Let the body settle before naming the answer.",
          "masteryMarker": "You remain physically steady without needing instant resolution."
        },
        {
          "branch": "Field",
          "name": "Friction Testing",
          "state": "Emerging",
          "description": "The surrounding field becomes easier to read when the pattern is not forced.",
          "effect": "Confusion becomes organized through timing, response, and visible feedback.",
          "developmentCue": "Let the field show which pieces belong together.",
          "masteryMarker": "The pattern can clarify without being mentally cornered."
        },
        {
          "branch": "Mastery",
          "name": "Learning Through Broken Fits",
          "state": "Mastery",
          "description": "The full path matures into clean resolution without premature closure.",
          "effect": "Clarity arrives with enough structure to support action.",
          "developmentCue": "Wait until the pattern can carry the next move.",
          "masteryMarker": "You complete the thought only when the form is ready."
        }
      ]
    },
    {
      "id": "perk-tree-64-4-v2",
      "mainQuestId": "purpose-64-4",
      "mainQuestName": "Pattern Resolution",
      "sourceLine": "Purpose · Design Earth · I Ching 64.4",
      "questState": "Arranging",
      "subtitle": "Develop the capacities behind Shared Mental Framework.",
      "nodes": [
        {
          "branch": "Root",
          "name": "Pattern Resolution",
          "state": "Core",
          "description": "This path develops the ability to turn incomplete mental pressure into usable clarity through shared mental framework.",
          "effect": "Confusion becomes workable when the pattern is not forced into false certainty.",
          "developmentCue": "Notice the difference between pressure and real pattern.",
          "masteryMarker": "Unfinished information can be held without rushing into closure."
        },
        {
          "branch": "Awareness",
          "name": "Shared Framing",
          "state": "Emerging",
          "description": "You learn to notice which part of the pattern is actually visible.",
          "effect": "Fragments stop pretending to be the whole picture.",
          "developmentCue": "Identify the clearest piece without enlarging it.",
          "masteryMarker": "You can separate a real signal from a completed story."
        },
        {
          "branch": "Embodiment",
          "name": "Collaborative Sorting",
          "state": "Emerging",
          "description": "The body learns to stay steady while the mind has not finished sorting.",
          "effect": "Action slows enough for real structure to appear.",
          "developmentCue": "Let the body settle before naming the answer.",
          "masteryMarker": "You remain physically steady without needing instant resolution."
        },
        {
          "branch": "Field",
          "name": "Communicable Structure",
          "state": "Emerging",
          "description": "The surrounding field becomes easier to read when the pattern is not forced.",
          "effect": "Confusion becomes organized through timing, response, and visible feedback.",
          "developmentCue": "Let the field show which pieces belong together.",
          "masteryMarker": "The pattern can clarify without being mentally cornered."
        },
        {
          "branch": "Mastery",
          "name": "Making Confusion Discussable",
          "state": "Mastery",
          "description": "The full path matures into clean resolution without premature closure.",
          "effect": "Clarity arrives with enough structure to support action.",
          "developmentCue": "Wait until the pattern can carry the next move.",
          "masteryMarker": "You complete the thought only when the form is ready."
        }
      ]
    },
    {
      "id": "perk-tree-64-5-v2",
      "mainQuestId": "purpose-64-5",
      "mainQuestName": "Pattern Resolution",
      "sourceLine": "Purpose · Design Earth · I Ching 64.5",
      "questState": "Pressurized",
      "subtitle": "Develop the capacities behind Projected Resolution.",
      "nodes": [
        {
          "branch": "Root",
          "name": "Pattern Resolution",
          "state": "Core",
          "description": "This path develops the ability to turn incomplete mental pressure into usable clarity through projected resolution.",
          "effect": "Confusion becomes workable when the pattern is not forced into false certainty.",
          "developmentCue": "Notice the difference between pressure and real pattern.",
          "masteryMarker": "Unfinished information can be held without rushing into closure."
        },
        {
          "branch": "Awareness",
          "name": "Projected Clarity",
          "state": "Emerging",
          "description": "You learn to notice which part of the pattern is actually visible.",
          "effect": "Fragments stop pretending to be the whole picture.",
          "developmentCue": "Identify the clearest piece without enlarging it.",
          "masteryMarker": "You can separate a real signal from a completed story."
        },
        {
          "branch": "Embodiment",
          "name": "Pressure Boundaries",
          "state": "Emerging",
          "description": "The body learns to stay steady while the mind has not finished sorting.",
          "effect": "Action slows enough for real structure to appear.",
          "developmentCue": "Let the body settle before naming the answer.",
          "masteryMarker": "You remain physically steady without needing instant resolution."
        },
        {
          "branch": "Field",
          "name": "Responsible Synthesis",
          "state": "Emerging",
          "description": "The surrounding field becomes easier to read when the pattern is not forced.",
          "effect": "Confusion becomes organized through timing, response, and visible feedback.",
          "developmentCue": "Let the field show which pieces belong together.",
          "masteryMarker": "The pattern can clarify without being mentally cornered."
        },
        {
          "branch": "Mastery",
          "name": "Speaking Partial Truth Cleanly",
          "state": "Mastery",
          "description": "The full path matures into clean resolution without premature closure.",
          "effect": "Clarity arrives with enough structure to support action.",
          "developmentCue": "Wait until the pattern can carry the next move.",
          "masteryMarker": "You complete the thought only when the form is ready."
        }
      ]
    },
    {
      "id": "perk-tree-64-6-v2",
      "mainQuestId": "purpose-64-6",
      "mainQuestName": "Pattern Resolution",
      "sourceLine": "Purpose · Design Earth · I Ching 64.6",
      "questState": "Suspended",
      "subtitle": "Develop the capacities behind Completion Without Closure.",
      "nodes": [
        {
          "branch": "Root",
          "name": "Pattern Resolution",
          "state": "Core",
          "description": "This path develops the ability to turn incomplete mental pressure into usable clarity through completion without closure.",
          "effect": "Confusion becomes workable when the pattern is not forced into false certainty.",
          "developmentCue": "Notice the difference between pressure and real pattern.",
          "masteryMarker": "Unfinished information can be held without rushing into closure."
        },
        {
          "branch": "Awareness",
          "name": "Final-Stage Discernment",
          "state": "Emerging",
          "description": "You learn to notice which part of the pattern is actually visible.",
          "effect": "Fragments stop pretending to be the whole picture.",
          "developmentCue": "Identify the clearest piece without enlarging it.",
          "masteryMarker": "You can separate a real signal from a completed story."
        },
        {
          "branch": "Embodiment",
          "name": "Completion Restraint",
          "state": "Emerging",
          "description": "The body learns to stay steady while the mind has not finished sorting.",
          "effect": "Action slows enough for real structure to appear.",
          "developmentCue": "Let the body settle before naming the answer.",
          "masteryMarker": "You remain physically steady without needing instant resolution."
        },
        {
          "branch": "Field",
          "name": "Timing Protection",
          "state": "Emerging",
          "description": "The surrounding field becomes easier to read when the pattern is not forced.",
          "effect": "Confusion becomes organized through timing, response, and visible feedback.",
          "developmentCue": "Let the field show which pieces belong together.",
          "masteryMarker": "The pattern can clarify without being mentally cornered."
        },
        {
          "branch": "Mastery",
          "name": "Completing Only When Ready",
          "state": "Mastery",
          "description": "The full path matures into clean resolution without premature closure.",
          "effect": "Clarity arrives with enough structure to support action.",
          "developmentCue": "Wait until the pattern can carry the next move.",
          "masteryMarker": "You complete the thought only when the form is ready."
        }
      ]
    }
  ],
  "qaAudit": {
    "referenceStandard": "59.2 V2 gold standard",
    "contentSchema": "MainQuestContentEntryV2 + MainQuestPerkTreeV2",
    "audits": [
      {
        "gateLine": "64.1",
        "score": 96,
        "status": "gold",
        "issues": []
      },
      {
        "gateLine": "64.2",
        "score": 96,
        "status": "gold",
        "issues": []
      },
      {
        "gateLine": "64.3",
        "score": 96,
        "status": "gold",
        "issues": []
      },
      {
        "gateLine": "64.4",
        "score": 96,
        "status": "gold",
        "issues": []
      },
      {
        "gateLine": "64.5",
        "score": 96,
        "status": "gold",
        "issues": []
      },
      {
        "gateLine": "64.6",
        "score": 96,
        "status": "gold",
        "issues": []
      }
    ]
  }
}